scrumy_cli/__init__.py
scrumy_cli/__main__.py
scrumy_cli/scrumy.py
scrumy_cli-0.4.dist-info/licenses/LICENSE
scrumy_cli-0.4.dist-info/METADATA
scrumy_cli-0.4.dist-info/WHEEL
scrumy_cli-0.4.dist-info/entry_points.txt
scrumy_cli-0.4.dist-info/top_level.txt
scrumy_cli-0.4.dist-info/RECORD
